voice_agent_core/__init__.py
voice_agent_core/actions.py
voice_agent_core/listening.py
voice_agent_core/llm.py
voice_agent_core/main.py
voice_agent_core/speaking.py
voice_agent_core-1.2.2.dist-info/licenses/LICENSE
voice_agent_core-1.2.2.dist-info/METADATA
voice_agent_core-1.2.2.dist-info/WHEEL
voice_agent_core-1.2.2.dist-info/top_level.txt
voice_agent_core-1.2.2.dist-info/RECORD
