Metadata-Version: 2.4
Name: voice-agent-core
Version: 1.2.2
Summary: A conversational voice companion bot framework for Python. Plug in any LLM and voice tools to create your own assistant.
Author-email: Darshan <darshanbr081@gmail.com>
License: MIT License
Project-URL: Homepage, https://github.com/Darshan0312/Voice_Agent
Project-URL: BugTracker, https://github.com/Darshan0312/Voice_agent/issues
Keywords: voice assistant,LLM,AI,companion bot,speech recognition,text to speech
Classifier: Programming Language :: Python :: 3
Classifier: License :: OSI Approved :: MIT License
Classifier: Operating System :: OS Independent
Requires-Python: >=3.8
License-File: LICENSE
Requires-Dist: SpeechRecognition>=3.14.3
Requires-Dist: pyttsx3>=2.90
Requires-Dist: pywhatkit>=5.4
Requires-Dist: PyAudio>=0.2.14
Requires-Dist: pydub>=0.25.1
Requires-Dist: soundfile>=0.12.1
Requires-Dist: requests>=2.31.0
Dynamic: license-file
